power_comparison/__init__.py
power_comparison/__main__.py
power_comparison/app.py
power_comparison/controller.py
power_comparison/data.py
power_comparison/default_values_utility.py
power_comparison/plan_comparison_screen.py
power_comparison/tkinter_figure.py
power_comparison/usage_view_screen.py
power_comparison/view.py
power_comparison/connectors/__init__.py
power_comparison/connectors/blank.py
power_comparison/connectors/connector.py
power_comparison/connectors/contact_energy_connector.py
power_comparison/img/cross_pattern.png
power_comparison/img/cross_pattern.svg
power_comparison/img/moon_icon.png
power_comparison/img/moon_icon.svg
power_comparison/img/power_compare.ico
power_comparison/img/power_compare.png
power_comparison/img/power_compare.svg
power_comparison/img/sun_icon.png
power_comparison/img/sun_icon.svg
power_comparison/profiles/example.csv
power_comparison/profiles/Christchurch-Dec-2024/Contact-Low-Good-Charge.csv
power_comparison/profiles/Christchurch-Dec-2024/Contact-Low-Good-Nights.csv
power_comparison/profiles/Christchurch-Dec-2024/Contact-Low-Good-Weekends.csv
power_comparison/profiles/Christchurch-Dec-2024/Contact-Low-Simple.csv
power_comparison/profiles/Christchurch-Dec-2024/Contact-Standard-Good-Charge.csv
power_comparison/profiles/Christchurch-Dec-2024/Contact-Standard-Good-Nights.csv
power_comparison/profiles/Christchurch-Dec-2024/Contact-Standard-Good-Weekends.csv
power_comparison/profiles/Christchurch-Dec-2024/Contact-Standard-Simple.csv
power_comparison/profiles/Christchurch-Dec-2024/Electric-Kiwi-Low-Kiwi.csv
power_comparison/profiles/Christchurch-Dec-2024/Electric-Kiwi-Low-Movemaster.csv
power_comparison/profiles/Christchurch-Dec-2024/Electric-Kiwi-Standard-Kiwi.csv
power_comparison/profiles/Christchurch-Dec-2024/Electric-Kiwi-Standard-Movemaster.csv
power_comparison/profiles/Christchurch-Dec-2024/Flick-Low-Flat.csv
power_comparison/profiles/Christchurch-Dec-2024/Flick-Low-Off-Peak.csv
power_comparison-1.0.8.dist-info/METADATA
power_comparison-1.0.8.dist-info/WHEEL
power_comparison-1.0.8.dist-info/entry_points.txt
power_comparison-1.0.8.dist-info/licenses/LICENSE
power_comparison-1.0.8.dist-info/RECORD
